vcchat.py
vcchat-0.0.1.dist-info/LICENSE
vcchat-0.0.1.dist-info/METADATA
vcchat-0.0.1.dist-info/WHEEL
vcchat-0.0.1.dist-info/top_level.txt
vcchat-0.0.1.dist-info/RECORD
