Metadata-Version: 2.1
Name: vcchat
Version: 0.0.1
Summary: chatbot
Author: aiml department
Author-email: aiml5thsem@gmail.com
License: MIT
Keywords: vcchat
Classifier: Programming Language :: Python :: 3
Classifier: License :: OSI Approved :: MIT License
Classifier: Operating System :: OS Independent
Requires-Python: >=3.7
License-File: LICENSE
Requires-Dist: openai
